csv_manager/__init__.py
csv_manager/database.py
csv_manager/datafile.py
csv_manager/misc.py
csv_manager/plotter.py
csv_manager/writer.py
csv_manager-0.11.9.dist-info/METADATA
csv_manager-0.11.9.dist-info/WHEEL
csv_manager-0.11.9.dist-info/top_level.txt
csv_manager-0.11.9.dist-info/RECORD
