Metadata-Version: 2.1
Name: csv-manager
Version: 0.11.9
Summary: A simple CSV importer/exporter with plotting capabilities with matplotlib
Home-page: https://github.com/AdelKS/csv_manager
Author: Adel KARA SLIMANE
Author-email: adel.ks@zegrapher.com
License: The Unlicense
Keywords: csv export import plot matplotlib
Platform: UNKNOWN
Requires-Dist: matplotlib
Requires-Dist: py-expression-eval
